pollination/alias/__init__.py
pollination/alias/inputs/__init__.py
pollination/alias/inputs/baseline.py
pollination/alias/inputs/bool_options.py
pollination/alias/inputs/comfort.py
pollination/alias/inputs/ddy.py
pollination/alias/inputs/emissions.py
pollination/alias/inputs/grid.py
pollination/alias/inputs/model.py
pollination/alias/inputs/north.py
pollination/alias/inputs/pit.py
pollination/alias/inputs/postprocess.py
pollination/alias/inputs/radiancepar.py
pollination/alias/inputs/runperiod.py
pollination/alias/inputs/schedule.py
pollination/alias/inputs/simulation.py
pollination/alias/inputs/view.py
pollination/alias/inputs/wea.py
pollination/alias/outputs/__init__.py
pollination/alias/outputs/comfort.py
pollination/alias/outputs/daylight.py
pollination/alias/outputs/eui.py
pollination/alias/outputs/summary.py
pollination_alias-0.11.15.dist-info/LICENSE
pollination_alias-0.11.15.dist-info/METADATA
pollination_alias-0.11.15.dist-info/WHEEL
pollination_alias-0.11.15.dist-info/top_level.txt
pollination_alias-0.11.15.dist-info/RECORD
