Metadata-Version: 2.1
Name: pollination-alias
Version: 0.11.15
Summary: Collection of alias inputs and outputs for Pollination recipes.
Home-page: https://github.com/pollination/pollination-alias
Author: Pollination
Author-email: info@pollination.cloud
License: Apache-2.0 License
Classifier: Programming Language :: Python :: 3.7
Classifier: Programming Language :: Python :: Implementation :: CPython
Classifier: Operating System :: OS Independent
Classifier: License :: OSI Approved :: Apache Software License
License-File: LICENSE
Requires-Dist: pollination-dsl>=0.14.1
